ovos_ww_plugin_precise_onnx/__init__.py
ovos_ww_plugin_precise_onnx/inference.py
ovos_ww_plugin_precise_onnx/version.py
ovos_ww_plugin_precise_onnx-0.1.0.dist-info/licenses/LICENSE
ovos_ww_plugin_precise_onnx-0.1.0.dist-info/METADATA
ovos_ww_plugin_precise_onnx-0.1.0.dist-info/WHEEL
ovos_ww_plugin_precise_onnx-0.1.0.dist-info/entry_points.txt
ovos_ww_plugin_precise_onnx-0.1.0.dist-info/top_level.txt
ovos_ww_plugin_precise_onnx-0.1.0.dist-info/zip-safe
ovos_ww_plugin_precise_onnx-0.1.0.dist-info/RECORD
