Metadata-Version: 2.4
Name: ovos_ww_plugin_precise_onnx
Version: 0.1.0
Summary: A wake word plugin for OpenVoiceOS
Home-page: https://github.com/OpenVoiceOS/ovos-ww-plugin-precise-onnx
Author: JarbasAi
Author-email: jarbasai@mailfence.com
License: Apache-2.0
Keywords: mycroft ovos plugin wake word
Classifier: License :: OSI Approved :: Apache Software License
License-File: LICENSE
Requires-Dist: onnxruntime
Requires-Dist: sonopy
Requires-Dist: ovos-plugin-manager<3.0.0,>=1.0.0
Requires-Dist: ovos-utils<1.0.0,>=0.0.14
Dynamic: author
Dynamic: author-email
Dynamic: classifier
Dynamic: home-page
Dynamic: keywords
Dynamic: license
Dynamic: license-file
Dynamic: requires-dist
Dynamic: summary
